LICENCE
README.md
setup.py
basic_components_fpp/__init__.py
basic_components_fpp/exception.py
basic_components_fpp/request.py
basic_components_fpp.egg-info/PKG-INFO
basic_components_fpp.egg-info/SOURCES.txt
basic_components_fpp.egg-info/dependency_links.txt
basic_components_fpp.egg-info/requires.txt
basic_components_fpp.egg-info/top_level.txt