Metadata-Version: 2.4
Name: basic_components_fpp
Version: 0.0.1
Summary: This project aims to share components and features that would be replicated in most Python projects.
Author: Lucas de Souza e Sousa
Author-email: lucas11souza97@gmail.com
License: MIT License
Keywords: basic components python projcts
License-File: LICENCE
Requires-Dist: requests
Dynamic: author
Dynamic: author-email
Dynamic: description
Dynamic: description-content-type
Dynamic: keywords
Dynamic: license
Dynamic: license-file
Dynamic: requires-dist
Dynamic: summary
